RPGshare/__init__.py
RPGshare/board.py
RPGshare/exceptions.py
RPGshare/setup.py
RPGshare/utils.py
rpgshare-0.1.1.dist-info/METADATA
rpgshare-0.1.1.dist-info/WHEEL
rpgshare-0.1.1.dist-info/top_level.txt
rpgshare-0.1.1.dist-info/RECORD
