Metadata-Version: 2.4
Name: RPGshare
Version: 0.1.1
Summary: 中信证券榜单数据获取与处理库
Home-page: 
Author: tedelon
License: MIT
Classifier: Programming Language :: Python :: 3
Classifier: License :: OSI Approved :: MIT License
Classifier: Operating System :: OS Independent
Requires-Python: >=3.6
Requires-Dist: requests
Dynamic: author
Dynamic: classifier
Dynamic: license
Dynamic: requires-dist
Dynamic: requires-python
Dynamic: summary
